odin/__init__.py
odin/odin.py
odin/track.py
odin/traffic_analysis.py
vodin-0.0.3.dist-info/LICENSE
vodin-0.0.3.dist-info/WHEEL
vodin-0.0.3.dist-info/METADATA
vodin-0.0.3.dist-info/RECORD
